socrata2sql/__init__.py
socrata2sql/cli.py
socrata2sql/exceptions.py
socrata2sql/parsers.py
socrata2sql/ui.py
socrata2sql-0.1.4.dist-info/LICENSE
socrata2sql-0.1.4.dist-info/METADATA
socrata2sql-0.1.4.dist-info/WHEEL
socrata2sql-0.1.4.dist-info/entry_points.txt
socrata2sql-0.1.4.dist-info/top_level.txt
socrata2sql-0.1.4.dist-info/RECORD
